<?xml version="1.0" encoding="utf-8"?>
<wine_list>
  <wine>
    <tag>0PA00AAAB46601</tag>
    <vendor>Prooftag SAS</vendor>
    <model>Montre de luxe</model>
    <date>15/01/2035</date>
  </wine>
  <wine>
    <tag>0PA00AAAB46602</tag>
    <vendor>Prooftag SAS</vendor>
    <model>Montre de luxe</model>
    <date>15/01/2035</date>
  </wine>
    <wine>
    <tag>0PA00AAAB46603</tag>
    <vendor>Prooftag SAS</vendor>
    <model>Montre de luxe</model>
    <date>15/01/2035</date>
  </wine>
  <wine>
    <tag>0PA00AAAB46604</tag>
    <vendor>Prooftag SAS</vendor>
    <model>Montre de luxe</model>
    <date>15/01/2035</date>
  </wine>
  <wine>
    <tag>0PA00AAAB46605</tag>
    <vendor>Prooftag SAS</vendor>
    <model>Montre de luxe</model>
    <date>15/01/2035</date>
  </wine>
  <wine>
    <tag>0PA00AAAB46606</tag>
    <vendor>Prooftag SAS</vendor>
    <model>Montre de luxe</model>
    <date>15/01/2035</date>
  </wine>
  <wine>
    <tag>0PA00AAAB46607</tag>
    <vendor>Prooftag SAS</vendor>
    <model>Montre de luxe</model>
    <date>15/01/2035</date>
  </wine>
  <wine>
    <tag>0PA00AAAB46608</tag>
    <vendor>Prooftag SAS</vendor>
    <model>Montre de luxe</model>
    <date>15/01/2035</date>
  </wine>
  <wine>
    <tag>0PA00AAAB46609</tag>
    <vendor>Prooftag SAS</vendor>
    <model>Montre de luxe</model>
    <date>15/01/2035</date>
  </wine>
  <wine>
    <tag>0PA00AAAB46610</tag>
    <vendor>Prooftag SAS</vendor>
    <model>Montre de luxe</model>
    <date>15/01/2035</date>
  </wine>
  <wine>
    <tag>0PA00AAAB46600</tag>
    <vendor>Prooftag SAS</vendor>
    <model>Montre de luxe</model>
    <date>15/01/2035</date>
  </wine>
</wine_list>